[
  {
    "id": "1765984473651-a3j3epi",
    "username": "Crypto Emperor",
    "text": "0.60 #Bitcoin \n\nA person who retweets, follows me will receive 0.60 $BTC ( $50.000 ) (yes, for real)\n\nRetweet my pinned post",
    "likes": 106,
    "retweets": 96,
    "replies": 98,
    "views": 0,
    "timestamp": "2025-12-17T12:03:00.000Z"
  },
  {
    "id": "1765984473654-fikvq66",
    "username": "Trending Bitcoin",
    "text": "Everyone will be a millionaire eventually  \n\nAlmost nobody will own 1 Bitcoin",
    "likes": 333,
    "retweets": 68,
    "replies": 29,
    "views": 0,
    "timestamp": "2025-12-16T02:06:00.000Z"
  },
  {
    "id": "1765984473656-1jplgly",
    "username": "Crypto Pump",
    "text": "for lucky 4 people \n$10,000 #Bitcoin         \n\nLike\n\nFollow\n\nRT",
    "likes": 76,
    "retweets": 63,
    "replies": 51,
    "views": 0,
    "timestamp": "2025-12-17T12:15:44.000Z"
  },
  {
    "id": "1765984473671-4p1ly85",
    "username": "Vivek Sen",
    "text": "#BITCOIN IS RIPPING \n\nWE ARE SOO BACK",
    "likes": 92,
    "retweets": 17,
    "replies": 26,
    "views": 0,
    "timestamp": "2025-12-17T15:07:24.000Z"
  },
  {
    "id": "1765984473673-p7rvu82",
    "username": "Sweep",
    "text": "Me checking on the homies I shilled Bitcoin to at 125k",
    "likes": 7649,
    "retweets": 525,
    "replies": 267,
    "views": 0,
    "timestamp": "2025-12-15T18:39:58.000Z"
  },
  {
    "id": "1765984473674-50sutkl",
    "username": "comet",
    "text": "2021-2024: Bitcoin up 100%\n\n2025: Bitcoin down 30%\n\nI miss Joe Biden!",
    "likes": 89,
    "retweets": 19,
    "replies": 32,
    "views": 0,
    "timestamp": "2025-12-17T14:47:36.000Z"
  },
  {
    "id": "1765984473675-cps2phn",
    "username": "The ₿itcoin Therapist",
    "text": "Me buying more bitcoin at $87,000 while everyone else sells because of quantum FUD",
    "likes": 581,
    "retweets": 54,
    "replies": 62,
    "views": 0,
    "timestamp": "2025-12-16T17:21:28.000Z"
  },
  {
    "id": "1765984473676-mg68b58",
    "username": "The Bitcoin Historian",
    "text": "LIKE, IF YOU BOUGHT THE #BITCOIN DIP",
    "likes": 48,
    "retweets": 3,
    "replies": 9,
    "views": 0,
    "timestamp": "2025-12-17T15:09:45.000Z"
  },
  {
    "id": "1765984473677-cxpd99i",
    "username": "Daniel Batten",
    "text": "Bhutan is empirically dismantling almost every theoretical argument used against Bitcoin\n\nIt's economy is thriving, and it is now using its Bitcoin stack to build a sustainable Mindfulness City\n\nIt is not selling its Bitcoin, but using it for collateral and risk-managed yield",
    "likes": 19,
    "retweets": 8,
    "replies": 1,
    "views": 0,
    "timestamp": "2025-12-17T14:53:37.000Z"
  },
  {
    "id": "1765984476323-wrhuxre",
    "username": "Quinten | 048.eth",
    "text": "Bitcoin sharks just bought at the most aggressive pace in 13 years",
    "likes": 448,
    "retweets": 70,
    "replies": 63,
    "views": 0,
    "timestamp": "2025-12-17T11:26:10.000Z"
  },
  {
    "id": "1765984476323-yf707zr",
    "username": "BlockNews",
    "text": "BITCOIN $BTC JUST SURGED $3,000 IN LESS THAN 20 MINUTES TO RECLAIM $90,000 \n\nARE WE BACK?",
    "likes": 7,
    "retweets": 0,
    "replies": 1,
    "views": 0,
    "timestamp": "2025-12-17T15:12:19.000Z"
  },
  {
    "id": "1765984476324-aypj7z9",
    "username": "Bitcoin Archive",
    "text": "JUST IN: Bitcoin surges over $90,000\n\n$100k by Christmas?",
    "likes": 77,
    "retweets": 6,
    "replies": 42,
    "views": 0,
    "timestamp": "2025-12-17T15:10:29.000Z"
  },
  {
    "id": "1765984476325-w65ol2z",
    "username": "Chill Trader",
    "text": "Bitcoin is still attempting to regain its previous support level.\nUntil we see a clean acceptance above it, this is just a reaction, not a trend shift.",
    "likes": 4,
    "retweets": 1,
    "replies": 0,
    "views": 0,
    "timestamp": "2025-12-17T14:43:17.000Z"
  },
  {
    "id": "1765984478948-38q5yz4",
    "username": "Trending Bitcoin",
    "text": "Jack Mallers broke the bull meter on live TV\n\n“#Bitcoin isn’t going for $150K, it’s going for everything.”  \n\nA $400-$500 trillion savings market… and we’re only at $2.43T today.  \n\nThat’s a 100x to 200x $BTC runway. You’re not bullish enough.",
    "likes": 66,
    "retweets": 10,
    "replies": 12,
    "views": 0,
    "timestamp": "2025-12-17T14:05:00.000Z"
  },
  {
    "id": "1765984478949-oe5or8r",
    "username": "NoLimit",
    "text": "JAPAN WILL CRASH BITCOIN IN 2 DAYS!!!\n\nIf you're holding BTC, you need to see this.\n\nOn December 19th (this Friday), the Bank of Japan (BOJ) is widely expected to raise interest rates.\n\nPotentially to 0.75%, the highest in DECADES.\n\nHere’s exactly what it means for your bags:",
    "likes": 1009,
    "retweets": 235,
    "replies": 204,
    "views": 0,
    "timestamp": "2025-12-17T10:23:19.000Z"
  },
  {
    "id": "1765984478950-q9b97rd",
    "username": "Mr. Bitcoin Whale",
    "text": "Giving away 5,000 $XRP to one lucky follower \n\nFound my old #XRP wallet from 2017 and decided to change someone’s life today.\n\nSimply like, retweet and comment \"done\".\n\nRandom winner in 24 hours, must be following.",
    "likes": 339,
    "retweets": 254,
    "replies": 254,
    "views": 0,
    "timestamp": "2025-12-16T14:10:39.000Z"
  },
  {
    "id": "1765984478950-focjf22",
    "username": "Bitcoin Price",
    "text": "Bitcoin Price: $90,000",
    "likes": 23,
    "retweets": 5,
    "replies": 4,
    "views": 0,
    "timestamp": "2025-12-17T15:06:20.000Z"
  },
  {
    "id": "1765984478951-92nadvt",
    "username": "Sumit Gupta (CoinDCX)",
    "text": "What the @CoinDCX team wants from their Secret Santa \n\nMost popular items:\n-Porsche 911\n-10 Bitcoin or Lambo\n-Thodi si respect\n-WFH for 2 days/week\n-PS5\n\nHopefully Santa will deliver!\n\nWhat do you want for christmas?",
    "likes": 49,
    "retweets": 2,
    "replies": 18,
    "views": 0,
    "timestamp": "2025-12-17T09:43:59.000Z"
  },
  {
    "id": "1765984478952-phedb4w",
    "username": "PlanB",
    "text": "Why is bitcoin not pumping?\n\nBecause 50% is selling (OGs traumatized by 2021, technical investors looking at RSI, 4y cycle fans expecting a bear 2y post halving) while the other 50% is buying (fundamental investors, tradfi, banks).\n\nEpic battle ... until sellers are out of ammo.",
    "likes": 4841,
    "retweets": 567,
    "replies": 322,
    "views": 0,
    "timestamp": "2025-12-16T19:56:05.000Z"
  },
  {
    "id": "1765984478952-zhw2c4i",
    "username": "Crypto Rover",
    "text": "BITCOIN BREAKS $89,000",
    "likes": 281,
    "retweets": 39,
    "replies": 106,
    "views": 0,
    "timestamp": "2025-12-17T14:56:47.000Z"
  },
  {
    "id": "1765984478953-vo44vbc",
    "username": "Trending Bitcoin",
    "text": "#BITCOIN RAINBOW CHART PREDICTS $150K to $440K in 2026",
    "likes": 437,
    "retweets": 82,
    "replies": 42,
    "views": 0,
    "timestamp": "2025-12-17T11:03:00.000Z"
  },
  {
    "id": "1765984478954-hzto0pv",
    "username": "Trending Bitcoin",
    "text": "Mother recorded her son buying his millionth #Bitcoin worth only $1,000 in 2009.\n\nSource: AI",
    "likes": 116,
    "retweets": 28,
    "replies": 11,
    "views": 0,
    "timestamp": "2025-12-17T12:03:00.000Z"
  },
  {
    "id": "1765984481541-u2snm1l",
    "username": "Jack Mallers",
    "text": "Twenty One is a Bitcoin company. Bitcoin is the best money in human history. We're building for that future.\n\nIf we can fix the money, we can fix the world. A mission large enough to last many lifetimes.\n\nWho we are, our mission, and what we’re building remain the same.",
    "likes": 1179,
    "retweets": 113,
    "replies": 78,
    "views": 0,
    "timestamp": "2025-12-16T23:47:10.000Z"
  },
  {
    "id": "1765984481542-owflrhb",
    "username": "Bitcoin.com News",
    "text": "1/ Special offer for new WhiteBIT users\n\nWhiteBIT has launched a limited-time promotion with 224% APR on USDC — a great way to explore Earn products and start generating passive income.\n\nhttps://app.adjust.com/1vmzyjyl?campaign=bitcoin_com_twitter_224_direct_app&adgroup=bitcoin_com…",
    "likes": 18,
    "retweets": 5,
    "replies": 14,
    "views": 0,
    "timestamp": "2025-12-17T12:09:34.000Z"
  },
  {
    "id": "1765984481542-652bebu",
    "username": "Shehzan",
    "text": "My favorite part of running Lava is hearing stories from our users. \n\nWe see a ton of use cases, but two always stand out to me-- when people buy homes for their families or use Lava to fund their expenses in retirement. \n\nBoth are a testament to how saving in bitcoin can drive",
    "likes": 9,
    "retweets": 0,
    "replies": 1,
    "views": 0,
    "timestamp": "2025-12-16T23:02:05.000Z"
  },
  {
    "id": "1765984481543-3qdvc23",
    "username": "Pu₹vesh | SEBI Reg RA",
    "text": "#btc\n\nek handle deekha do jo advance me bola ho that bitcoin will move sideways for 3 weeks.#BTC hit 93k and touched the upper side of the cloud.\nHope you guys enjoyed the view and made some decent money trading both sides of Bitcoin.\n\nMoves captured so far:\n 125k → 81k\n 81k → 93k\n\nNow expecting a sideways range between 80k–94k for a few days to up to 3 weeks.  x.com/TA_Purvesh/sta…",
    "likes": 37,
    "retweets": 5,
    "replies": 6,
    "views": 0,
    "timestamp": "2025-12-14T06:36:03.000Z"
  },
  {
    "id": "1765984481543-pl2y2pi",
    "username": "Bonafide Brand",
    "text": "If I handed you $200,000 today, where would you invest it?\n#Gold or #Bitcoin — and why?",
    "likes": 50,
    "retweets": 39,
    "replies": 33,
    "views": 0,
    "timestamp": "2025-12-17T13:59:11.000Z"
  },
  {
    "id": "1765984481543-yh5xbdn",
    "username": "Wealth Squad Chris",
    "text": "Bought 27 Bitcoin for $88,400\n\nMore Bitcoin is more purchasing power, more purchasing power is more freedom",
    "likes": 918,
    "retweets": 46,
    "replies": 99,
    "views": 0,
    "timestamp": "2025-12-16T21:34:52.000Z"
  },
  {
    "id": "1765984484203-w0yfu4x",
    "username": "Crypto Rover",
    "text": "BITCOIN BREAKS $90,000",
    "likes": 144,
    "retweets": 11,
    "replies": 39,
    "views": 0,
    "timestamp": "2025-12-17T15:07:12.000Z"
  },
  {
    "id": "1765984484204-1b0ly8c",
    "username": "Jax",
    "text": "#Bitcoin Finally dumped below $89,000 !  \n\nAs promised, I want to change someone's life and send 1 $BTC (~$89,000) to one person by tomorrow.   \n\nJust like, retweet and comment 'done'.  \n\nRandom winner in 15 hrs",
    "likes": 850,
    "retweets": 607,
    "replies": 591,
    "views": 0,
    "timestamp": "2025-12-14T22:08:07.000Z"
  },
  {
    "id": "1765984484204-6wfhwqy",
    "username": "SoSoValue",
    "text": "Thoughts from a friend in the community with 20+ years of successful investment experience:\n\nFifteen years ago today, Satoshi Nakamoto logged into the Bitcoin forum for the last time and vanished. No manifesto, no grand vision, not even a \"good luck.\"\n\nThe moment he disappeared,",
    "likes": 36770,
    "retweets": 14126,
    "replies": 8742,
    "views": 0,
    "timestamp": "2025-12-14T14:18:50.000Z"
  },
  {
    "id": "1765984484205-wcd5cx4",
    "username": "Trending Bitcoin",
    "text": "1 dot = 10,000 transactions",
    "likes": 896,
    "retweets": 131,
    "replies": 279,
    "views": 0,
    "timestamp": "2025-12-15T19:02:00.000Z"
  },
  {
    "id": "1765984486801-bw2jf8f",
    "username": "Pushpendra Singh Digital",
    "text": "BREAKING:  Saylor’s Strategy has snapped up $1.8 billion worth of Bitcoin in just the last two weeks.",
    "likes": 114,
    "retweets": 15,
    "replies": 23,
    "views": 0,
    "timestamp": "2025-12-15T14:38:04.000Z"
  },
  {
    "id": "1765984486802-r4nsp9o",
    "username": "Cake Wallet",
    "text": "\"They're treating you like a criminal just for acquiring Bitcoin. Taking your ID, your utility bill—as if you've already committed a crime.\"\n\n@vikrantnyc breaks down the KYC problem at @BitcoinConfEUR",
    "likes": 114,
    "retweets": 13,
    "replies": 11,
    "views": 0,
    "timestamp": "2025-12-17T13:00:02.000Z"
  },
  {
    "id": "1765984486802-qlt233r",
    "username": "CRYPTO₿IRB",
    "text": "POV: bought bitcoin below $19,000",
    "likes": 82,
    "retweets": 3,
    "replies": 20,
    "views": 0,
    "timestamp": "2025-12-17T12:02:56.000Z"
  },
  {
    "id": "1765984486802-e4q71i1",
    "username": "WazirX: India Ka Bitcoin Exchange",
    "text": "Aster deposits are live   \n\nYou can now deposit $ASTER on WazirX. \n\nAster will be listed later today! @Aster_DEX  \n\nOrder placement will begin at 2 PM IST.\n\nRepost & spread the word",
    "likes": 66,
    "retweets": 11,
    "replies": 43,
    "views": 0,
    "timestamp": "2025-12-17T06:17:30.000Z"
  },
  {
    "id": "1765984486803-0q34wk7",
    "username": "Crypto GVR",
    "text": "If #Bitcoin won’t break 95K$ this week then next stop will be 77K$ \n\nThis week is a crucial week for the market",
    "likes": 356,
    "retweets": 50,
    "replies": 44,
    "views": 0,
    "timestamp": "2025-12-15T04:10:51.000Z"
  },
  {
    "id": "1765984486803-58n3lgi",
    "username": "Lexi Bitcoin",
    "text": "Most chains add bridges.\n\nVery few rethink what privacy looks like once your asset leaves home turf.\n\nWhat @BeldexCoin just enabled isn’t just mobility for $BDX it’s mobility without losing the core guarantee that made the asset valuable in the first place.\n\nMoving acrossBeldex unlocks seamless cross-chain transfers with @StargateFinance\n\n$BDX now moves across @Ethereum, @BNBChain, @Solana, @Base, and @Arbitrum networks",
    "likes": 81,
    "retweets": 4,
    "replies": 73,
    "views": 0,
    "timestamp": "2025-12-17T06:34:01.000Z"
  },
  {
    "id": "1765984486803-vfwrcf0",
    "username": "matthew sigel, recovering CFA",
    "text": "Getting questions from clients about recent Bitcoin “death cross”, so worth showing the data:\n\nSince 2011:\n>Many occurred near major bottoms (2011, 2015, 2020, 2023)\n>6-month median subsequent return: +30%\n>12-month median: +89%\n>Positive hit rate: 64%\n\nLagging indicator.",
    "likes": 144,
    "retweets": 17,
    "replies": 17,
    "views": 0,
    "timestamp": "2025-12-16T18:42:45.000Z"
  },
  {
    "id": "1765984486804-x4d4q64",
    "username": "Lark Davis",
    "text": "Bitcoin This Is Very Weird  BITUNIX TRADE THE TOP COINS (available everywhere) $10,000 DEPOSIT BONUS   https://cryptolark.co/BITUNIX    Join The Inner Circle https://cryptolark.co/INNERCIRCLE",
    "likes": 40,
    "retweets": 8,
    "replies": 25,
    "views": 0,
    "timestamp": "2025-12-17T11:01:02.000Z"
  },
  {
    "id": "1765984486804-gzgknd5",
    "username": "Bull Theory",
    "text": "WHY IS BITCOIN STILL DUMPING WHILE INSTITUTIONS ARE MAKING BILLION DOLLAR BUYS?\n\nBitcoin is not going down because fundamentals are weak.\n\nIt is going down because selling pressure is stronger and coming from deeper sources.\n\nOne major reason is China’s mining crackdown coming",
    "likes": 269,
    "retweets": 69,
    "replies": 91,
    "views": 0,
    "timestamp": "2025-12-17T14:17:06.000Z"
  },
  {
    "id": "1765984489429-pome6c0",
    "username": "Trending Bitcoin",
    "text": "Unknown YouTube legend explaining how to buy #Bitcoin at $30 in 2011",
    "likes": 864,
    "retweets": 144,
    "replies": 20,
    "views": 0,
    "timestamp": "2025-12-16T00:09:00.000Z"
  },
  {
    "id": "1765984489430-5tjany5",
    "username": "Natalie Brunell",
    "text": "Bearish on big Bitcoin price predictions?\n\nDon’t miss my full interview with @mcclintock_m I think you’ll enjoy this timely conversation with Matt McClintock, founder of Bespoke Group.\n\nWe discuss Bitcoin price drivers, why whales have been selling, how much BTC will mean generational wealth, estate planning, wealth strategies, purpose and a new wealth hierarchy.",
    "likes": 20,
    "retweets": 4,
    "replies": 3,
    "views": 0,
    "timestamp": "2025-12-17T13:37:50.000Z"
  },
  {
    "id": "1765984489431-8b4acy4",
    "username": "Ali Charts",
    "text": "Whenever the SuperTrend flips to sell on the weekly chart, Bitcoin $BTC has historically responded with a major price drop.\n\n- February 2014:  -75% \n- January 2018: -73% \n- October 2019: -54% \n- May 2021: -38% \n- January 2022: -67%",
    "likes": 140,
    "retweets": 20,
    "replies": 29,
    "views": 0,
    "timestamp": "2025-12-16T10:28:00.000Z"
  },
  {
    "id": "1765984489431-4igpin2",
    "username": "Matthew R. Kratter",
    "text": "How To Become A Bitcoin NPC",
    "likes": 36,
    "retweets": 15,
    "replies": 5,
    "views": 0,
    "timestamp": "2025-12-17T14:32:37.000Z"
  },
  {
    "id": "1765984489432-6vm6dqo",
    "username": "Sjuul | AltCryptoGems",
    "text": "Every single time Japan hiked rates in the past, Bitcoin crashed:\n\nMarch '24 → -20%\nJuly '24 → -26%\nJan '25 → -30%\n\nThis Friday (Dec 19), they are likely doing it again. The consensus is 97% odds of a 25 bps hike.\n\nMost people are ignoring this. You shouldn't.\n\nHere is the",
    "likes": 610,
    "retweets": 6,
    "replies": 31,
    "views": 0,
    "timestamp": "2025-12-17T11:07:10.000Z"
  },
  {
    "id": "1765984489433-dxrxr12",
    "username": "Bitcoin Price",
    "text": "Bitcoin Price: $88,000",
    "likes": 18,
    "retweets": 2,
    "replies": 1,
    "views": 0,
    "timestamp": "2025-12-17T14:52:52.000Z"
  },
  {
    "id": "1765984489434-o8kuo8x",
    "username": "BATMAN",
    "text": "Bitcoin pumping hard!",
    "likes": 34,
    "retweets": 12,
    "replies": 7,
    "views": 0,
    "timestamp": "2025-12-17T14:54:44.000Z"
  },
  {
    "id": "1765984492053-2gx0ch1",
    "username": "naiive",
    "text": "new trader after buying Bitcoin at $126K for a quick flip",
    "likes": 4794,
    "retweets": 351,
    "replies": 120,
    "views": 0,
    "timestamp": "2025-12-15T14:21:23.000Z"
  },
  {
    "id": "1765984492054-9cci8xv",
    "username": "MartyParty",
    "text": "#Bitcoin High Timeframe - Dec 15th \n\nNotes: Wyckoff ditribution into Wyckoff Accumulation - waiting for the Spring\nWyckoff Spring will be a lower low to liquidate all accumulated longs, indication is the 50% pullback from the 3 head move on the Daily in the $78000-$80000 range.",
    "likes": 242,
    "retweets": 26,
    "replies": 37,
    "views": 0,
    "timestamp": "2025-12-15T16:55:05.000Z"
  }
]